pydataknot/__init__.py
pydataknot/data.py
pydataknot/feature_selection.py
pydataknot/mrmr.py
pydataknot/optimize_classifier.py
pydataknot/train_classifier.py
pydataknot/utils.py
pydataknot/config/__init__.py
pydataknot-0.0.3.dist-info/METADATA
pydataknot-0.0.3.dist-info/WHEEL
pydataknot-0.0.3.dist-info/entry_points.txt
pydataknot-0.0.3.dist-info/RECORD
