Metadata-Version: 2.4
Name: pydataknot
Version: 0.0.3
Summary: Add your description here
Requires-Python: >=3.9
Requires-Dist: flucoma-torch>=0.1.4
Requires-Dist: matplotlib>=3.9.4
Requires-Dist: scikit-learn>=1.6.1
Provides-Extra: dashboard
Requires-Dist: optuna-dashboard>=0.19.0; extra == 'dashboard'
